setup.py
timeouts/__init__.py
timeouts/socket.py
timeouts/time.py
timeouts.egg-info/PKG-INFO
timeouts.egg-info/SOURCES.txt
timeouts.egg-info/dependency_links.txt
timeouts.egg-info/top_level.txt