Metadata-Version: 1.0
Name: timeouts
Version: 0.2
Summary: Python Timeouts
Home-page: https://github.com/redbo/timeouts/
Author: Michael Barton
Author-email: mike@weirdlooking.com
License: BSD
Platform: any
